client/__init__.py
client/run_client.py
client/client/__init__.py
client/client/add_contact.py
client/client/client_db.py
client/client/del_contact.py
client/client/main_window.py
client/client/main_window_ui.py
client/client/start_dialog.py
client/client/transport.py
client/common/__init__.py
client/common/decos.py
client/common/errors.py
client/common/utils.py
client/common/variables.py
client/log/__init__.py
client/log/client_log_config.py
client/log/server_log_config.py
client/unit_tests/__init__.py
client/unit_tests/test_utils.py
simple_mess_client-0.1.0.dist-info/METADATA
simple_mess_client-0.1.0.dist-info/WHEEL
simple_mess_client-0.1.0.dist-info/top_level.txt
simple_mess_client-0.1.0.dist-info/RECORD
